flask_cos/__init__.py
flask_cos-2.1.6.dist-info/LICENSE
flask_cos-2.1.6.dist-info/METADATA
flask_cos-2.1.6.dist-info/WHEEL
flask_cos-2.1.6.dist-info/RECORD
