Metadata-Version: 2.1
Name: flask-cos
Version: 2.1.6
Summary: 腾讯云对象存储的Flask扩展
Home-page: https://github.com/codeif/flask-cos
License: MIT
Author: codeif
Author-email: me@codeif.com
Requires-Python: >=3.8,<4.0
Classifier: License :: OSI Approved :: MIT License
Classifier: Programming Language :: Python :: 3
Classifier: Programming Language :: Python :: 3.8
Classifier: Programming Language :: Python :: 3.9
Classifier: Programming Language :: Python :: 3.10
Classifier: Programming Language :: Python :: 3.11
Requires-Dist: flask
Requires-Dist: qcos
Requires-Dist: requests
Project-URL: Repository, https://github.com/codeif/flask-cos
